rypi/__init__.py
rypi/comm.py
rypi/conf.py
rypi/main.py
rypi/ryo/__init__.py
rypi/ryo/app.py
rypi/ryo/conf.py
rypi/ryo/core.py
rypi/ryo/db.py
rypi/ryo/file.py
rypi/ryo/main.py
rypi/ryo/ryo.py
rypi/ryo/user.py
rypi/ryto/__init__.py
rypi/ryto/amdd.py
rypi/ryto/c256.py
rypi/ryto/comm.py
rypi/ryto/conf.py
rypi/ryto/fatt.py
rypi/ryto/fren.py
rypi/ryto/fstr.py
rypi/ryto/main.py
rypi/ryto/mir.py
rypi/ryto/tfa.py
rypi/ryweb/__init__.py
rypi/ryweb/conf.py
rypi/ryweb/main.py
rypi/ryweb/router.py
rypi-2026.1.18.0.dist-info/METADATA
rypi-2026.1.18.0.dist-info/WHEEL
rypi-2026.1.18.0.dist-info/entry_points.txt
rypi-2026.1.18.0.dist-info/top_level.txt
rypi-2026.1.18.0.dist-info/RECORD
